{
  "noiseKey": {
    "private": {
      "type": "Buffer",
      "data": [
        224,
        205,
        203,
        118,
        1,
        6,
        203,
        27,
        123,
        94,
        3,
        117,
        241,
        80,
        131,
        47,
        227,
        49,
        17,
        243,
        150,
        232,
        146,
        186,
        208,
        48,
        205,
        192,
        21,
        157,
        134,
        104
      ]
    },
    "public": {
      "type": "Buffer",
      "data": [
        1,
        66,
        245,
        170,
        17,
        141,
        90,
        164,
        154,
        116,
        148,
        200,
        221,
        236,
        238,
        20,
        61,
        4,
        115,
        200,
        94,
        110,
        205,
        36,
        120,
        126,
        56,
        184,
        178,
        103,
        192,
        105
      ]
    }
  },
  "pairingEphemeralKeyPair": {
    "private": {
      "type": "Buffer",
      "data": [
        232,
        186,
        229,
        162,
        58,
        161,
        7,
        7,
        148,
        182,
        78,
        222,
        106,
        110,
        213,
        148,
        176,
        218,
        160,
        173,
        107,
        78,
        254,
        217,
        102,
        81,
        146,
        249,
        116,
        191,
        210,
        69
      ]
    },
    "public": {
      "type": "Buffer",
      "data": [
        206,
        159,
        93,
        173,
        131,
        98,
        39,
        163,
        69,
        105,
        115,
        231,
        56,
        6,
        60,
        49,
        138,
        100,
        86,
        178,
        88,
        0,
        19,
        7,
        139,
        237,
        134,
        115,
        197,
        237,
        32,
        61
      ]
    }
  },
  "signedIdentityKey": {
    "private": {
      "type": "Buffer",
      "data": [
        232,
        36,
        220,
        207,
        4,
        145,
        11,
        212,
        179,
        240,
        110,
        20,
        172,
        27,
        178,
        168,
        80,
        80,
        203,
        128,
        44,
        221,
        169,
        73,
        152,
        15,
        191,
        248,
        109,
        115,
        82,
        93
      ]
    },
    "public": {
      "type": "Buffer",
      "data": [
        38,
        24,
        145,
        107,
        141,
        36,
        250,
        77,
        107,
        107,
        219,
        56,
        100,
        212,
        73,
        55,
        48,
        81,
        77,
        72,
        114,
        174,
        99,
        127,
        223,
        43,
        39,
        179,
        179,
        21,
        146,
        15
      ]
    }
  },
  "signedPreKey": {
    "keyPair": {
      "private": {
        "type": "Buffer",
        "data": [
          40,
          169,
          62,
          98,
          80,
          163,
          16,
          107,
          177,
          123,
          15,
          104,
          236,
          186,
          28,
          15,
          71,
          135,
          91,
          163,
          230,
          88,
          46,
          193,
          73,
          202,
          197,
          120,
          43,
          156,
          53,
          109
        ]
      },
      "public": {
        "type": "Buffer",
        "data": [
          5,
          85,
          144,
          144,
          85,
          207,
          240,
          217,
          138,
          140,
          156,
          9,
          85,
          78,
          83,
          11,
          10,
          196,
          185,
          192,
          17,
          41,
          219,
          38,
          156,
          140,
          247,
          37,
          41,
          73,
          89,
          6
        ]
      }
    },
    "signature": {
      "type": "Buffer",
      "data": [
        196,
        100,
        220,
        242,
        249,
        128,
        223,
        249,
        250,
        240,
        8,
        116,
        148,
        96,
        97,
        165,
        59,
        214,
        46,
        180,
        165,
        16,
        226,
        59,
        5,
        16,
        219,
        216,
        253,
        1,
        93,
        3,
        31,
        5,
        228,
        97,
        35,
        64,
        240,
        203,
        109,
        178,
        5,
        101,
        187,
        204,
        126,
        169,
        8,
        30,
        23,
        48,
        250,
        60,
        6,
        212,
        149,
        97,
        127,
        41,
        201,
        51,
        233,
        131
      ]
    },
    "keyId": 1
  },
  "registrationId": 249,
  "advSecretKey": "DianPiuLQuHhyGMu/i6PUnZEGX/1AKyTLOnStwV6Ydc=",
  "processedHistoryMessages": [],
  "nextPreKeyId": 31,
  "firstUnuploadedPreKeyId": 31,
  "accountSyncCounter": 0,
  "accountSettings": {
    "unarchiveChats": false
  },
  "registered": true,
  "pairingCode": "SDC6PGDV",
  "me": {
    "id": "237672574738:92@s.whatsapp.net",
    "lid": "53373910945884:92@lid"
  },
  "account": {
    "details": "CIHW3vwCEMac3MAGGAEgACgA",
    "accountSignatureKey": "E5nKP2mn+hvoXFvcU8+Z1whzEYzs/XPpH54rrvhH0w4=",
    "accountSignature": "ws5Uz79A0lPLDvKOtEDzL/Xh1TCXNIj+KDzE7quOv3JP+UJknDme/c2ZqgvSLP4bAeYLub+nFDtPyEVKjKCjAg==",
    "deviceSignature": "8+1YnJ6utKGe/Wughovsckdmz9L0GVCXjV1o8WiO9aQBW+544SlNIdGKB9HQa99nlLknqFr20g+6XlPLHpakhg=="
  },
  "signalIdentities": [
    {
      "identifier": {
        "name": "237672574738:92@s.whatsapp.net",
        "deviceId": 0
      },
      "identifierKey": {
        "type": "Buffer",
        "data": [
          5,
          19,
          153,
          202,
          63,
          105,
          167,
          250,
          27,
          232,
          92,
          91,
          220,
          83,
          207,
          153,
          215,
          8,
          115,
          17,
          140,
          236,
          253,
          115,
          233,
          31,
          158,
          43,
          174,
          248,
          71,
          211,
          14
        ]
      }
    }
  ],
  "platform": "android",
  "routingInfo": {
    "type": "Buffer",
    "data": [
      8,
      18,
      8,
      5
    ]
  },
  "lastAccountSyncTimestamp": 1746341450,
  "lastPropHash": "nm3Bb"
}